cfitall/__init__.py
cfitall/manager.py
cfitall/registry.py
cfitall/utils.py
cfitall/providers/__init__.py
cfitall/providers/base.py
cfitall/providers/environment.py
cfitall/providers/filesystem.py
cfitall/tests/__init__.py
cfitall/tests/test_config.py
cfitall/tests/test_manager.py
cfitall/tests/test_provider_environment.py
cfitall/tests/test_provider_filesystem.py
cfitall/tests/test_utils.py
cfitall/tests/json/cfitall.json
cfitall/tests/json/cfitall.yml
cfitall/tests/yaml/cfitall.yml
cfitall/tests/yaml/extra.yaml
cfitall-2.0.1.dist-info/AUTHORS
cfitall-2.0.1.dist-info/LICENSE
cfitall-2.0.1.dist-info/METADATA
cfitall-2.0.1.dist-info/WHEEL
cfitall-2.0.1.dist-info/pbr.json
cfitall-2.0.1.dist-info/top_level.txt
cfitall-2.0.1.dist-info/RECORD
